Metadata-Version: 2.1
Name: qiskit-aqt-provider
Version: 1.14.0
Summary: Qiskit provider for AQT backends
Home-page: https://github.com/qiskit-community/qiskit-aqt-provider
License: Apache-2.0
Keywords: qiskit,sdk,quantum
Author: Qiskit Development Team
Requires-Python: >=3.9,<3.14
Classifier: Intended Audience :: Developers
Classifier: Intended Audience :: Science/Research
Classifier: License :: OSI Approved :: Apache Software License
Classifier: Operating System :: MacOS
Classifier: Operating System :: Microsoft :: Windows
Classifier: Operating System :: POSIX :: Linux
Classifier: Programming Language :: Python :: 3
Classifier: Programming Language :: Python :: 3.9
Classifier: Programming Language :: Python :: 3.10
Classifier: Programming Language :: Python :: 3.11
Classifier: Programming Language :: Python :: 3.12
Classifier: Programming Language :: Python :: 3 :: Only
Classifier: Programming Language :: Python :: 3.13
Classifier: Topic :: Scientific/Engineering
Provides-Extra: examples
Provides-Extra: test
Requires-Dist: annotated-types (>=0.7.0)
Requires-Dist: aqt-connector (==0.1.0)
Requires-Dist: httpx (>=0.24.0)
Requires-Dist: numpy (>=1) ; python_full_version > "3.9.0" and python_version < "3.13"
Requires-Dist: numpy (>=1,<2.1) ; python_full_version <= "3.9.0"
Requires-Dist: numpy (>=2.1) ; python_version >= "3.13"
Requires-Dist: platformdirs (>=3)
Requires-Dist: pydantic (>=2.5.0)
Requires-Dist: pydantic-core (>=2)
Requires-Dist: pytest (>=8) ; extra == "test"
Requires-Dist: pytest-httpx (>=0.35.0,<0.36.0) ; extra == "test"
Requires-Dist: python-dotenv (>=1)
Requires-Dist: qiskit (>=1,<2)
Requires-Dist: qiskit-aer (>=0.13.2)
Requires-Dist: qiskit-algorithms (>=0.2.1) ; extra == "examples"
Requires-Dist: qiskit-optimization (>=0.6.0) ; extra == "examples"
Requires-Dist: scipy (>=1,<1.15) ; python_version < "3.10"
Requires-Dist: scipy (>=1.15,<2.0) ; python_version >= "3.10"
Requires-Dist: tabulate (>=0.9.0)
Requires-Dist: tqdm (>=4)
Requires-Dist: typing-extensions (>=4.0.0)
Project-URL: Documentation, https://qiskit-community.github.io/qiskit-aqt-provider
Project-URL: Repository, https://github.com/qiskit-community/qiskit-aqt-provider
